cookiecutter.json
cookiecutter_poetry/__init__.py
cookiecutter_poetry/cli.py
hooks/post_gen_project.py
hooks/pre_gen_project.py
{{cookiecutter.project_name}}/.devcontainer/devcontainer.json
{{cookiecutter.project_name}}/.devcontainer/postCreateCommand.sh
{{cookiecutter.project_name}}/.editorconfig
{{cookiecutter.project_name}}/.github/actions/setup-poetry-env/action.yml
{{cookiecutter.project_name}}/.github/workflows/main.yml
{{cookiecutter.project_name}}/.github/workflows/on-release-main.yml
{{cookiecutter.project_name}}/.github/workflows/validate-codecov-config.yml
{{cookiecutter.project_name}}/.gitignore
{{cookiecutter.project_name}}/.pre-commit-config.yaml
{{cookiecutter.project_name}}/CONTRIBUTING.md
{{cookiecutter.project_name}}/Dockerfile
{{cookiecutter.project_name}}/LICENSE
{{cookiecutter.project_name}}/Makefile
{{cookiecutter.project_name}}/README.md
{{cookiecutter.project_name}}/codecov.yaml
{{cookiecutter.project_name}}/docs/index.md
{{cookiecutter.project_name}}/docs/modules.md
{{cookiecutter.project_name}}/mkdocs.yml
{{cookiecutter.project_name}}/poetry.toml
{{cookiecutter.project_name}}/pyproject.toml
{{cookiecutter.project_name}}/tests/test_foo.py
{{cookiecutter.project_name}}/tox.ini
{{cookiecutter.project_name}}/{{cookiecutter.project_slug}}/__init__.py
{{cookiecutter.project_name}}/{{cookiecutter.project_slug}}/foo.py
cookiecutter_poetry-0.8.0.dist-info/LICENSE
cookiecutter_poetry-0.8.0.dist-info/METADATA
cookiecutter_poetry-0.8.0.dist-info/WHEEL
cookiecutter_poetry-0.8.0.dist-info/entry_points.txt
cookiecutter_poetry-0.8.0.dist-info/RECORD
