Metadata-Version: 2.1
Name: cookiecutter-poetry
Version: 0.8.0
Summary: A python cookiecutter application to create a new python project that uses poetry to manage its dependencies.
Home-page: https://github.com/fpgmaas/cookiecutter-poetry
Keywords: cookiecutter,template,poetry
Author: Florian Maas
Author-email: fpgmaas@gmail.com
Requires-Python: >=3.8,<4.0
Classifier: Programming Language :: Python :: 3
Classifier: Programming Language :: Python :: 3.8
Classifier: Programming Language :: Python :: 3.9
Classifier: Programming Language :: Python :: 3.10
Classifier: Programming Language :: Python :: 3.11
Classifier: Programming Language :: Python :: 3.12
Requires-Dist: cookiecutter (>=2.1.1,<3.0.0)
Project-URL: Documentation, https://fpgmaas.github.io/cookiecutter-poetry/
Project-URL: Repository, https://github.com/fpgmaas/cookiecutter-poetry
